rumi.py
rumi-0.1.dist-info/WHEEL
rumi-0.1.dist-info/METADATA
rumi-0.1.dist-info/RECORD
