Metadata-Version: 2.1
Name: rumi
Version: 0.1
Summary: Rumi: tools for simplifying python development 
Home-page: https://github.com/kamyar/rumi
License: UNKNOWN
Author: Kamyar Ghasemlou
Author-email: rumi@kamy.me
